cabot_check_cloudwatch/__init__.py
cabot_check_cloudwatch/helpers.py
cabot_check_cloudwatch/models.py
cabot_check_cloudwatch/urls.py
cabot_check_cloudwatch/views.py
cabot_check_cloudwatch/migrations/0001_initial.py
cabot_check_cloudwatch/migrations/__init__.py
cabot_check_cloudwatch-0.1.2.dist-info/DESCRIPTION.rst
cabot_check_cloudwatch-0.1.2.dist-info/METADATA
cabot_check_cloudwatch-0.1.2.dist-info/RECORD
cabot_check_cloudwatch-0.1.2.dist-info/WHEEL
cabot_check_cloudwatch-0.1.2.dist-info/metadata.json
cabot_check_cloudwatch-0.1.2.dist-info/top_level.txt
