Metadata-Version: 2.0
Name: cabot-check-cloudwatch
Version: 0.1.2
Summary: A clouwatch check plugin for Cabot by Arachnys
Home-page: http://cabotapp.com
Author: Arachnys
Author-email: techteam@arachnys.com
License: UNKNOWN
Platform: UNKNOWN
Requires-Dist: boto3 (>=1.4.7)
